<?xml version='1.0' encoding='UTF-8'?><factura version='1.1.0' id='comprobante'><infoTributaria><ambiente>2</ambiente><tipoEmision>1</tipoEmision><razonSocial>OTAVALO UYAGUARI MANUEL EFRAIN</razonSocial><nombreComercial>OTAVALO UYAGUARI MANUEL EFRAIN</nombreComercial><ruc>0704642552001</ruc><claveAcceso>0106202301070464255200120010100000004031234567815</claveAcceso><codDoc>01</codDoc><estab>001</estab><ptoEmi>010</ptoEmi><secuencial>000000403</secuencial><dirMatriz>AZUAY Y MACHALA</dirMatriz></infoTributaria><infoFactura><fechaEmision>01/06/2023</fechaEmision><dirEstablecimiento>AZUAY Y MACAHALA</dirEstablecimiento><obligadoContabilidad>NO</obligadoContabilidad><tipoIdentificacionComprador>04</tipoIdentificacionComprador><razonSocialComprador>ANIMAL HOME MEDICVET CIA.LTDA.</razonSocialComprador><identificacionComprador>0791829747001</identificacionComprador><totalSinImpuestos>338.06</totalSinImpuestos><totalDescuento>0</totalDescuento><totalConImpuestos><totalImpuesto><codigo>2</codigo><codigoPorcentaje>2</codigoPorcentaje><baseImponible>338.06</baseImponible><valor>40.57</valor></totalImpuesto></totalConImpuestos><propina>0.00</propina><importeTotal>378.63</importeTotal><moneda>DOLAR</moneda><pagos><pago><formaPago>01</formaPago><total>378.63</total></pago></pagos></infoFactura><detalles><detalle><codigoPrincipal>ang. pe.001</codigoPrincipal><descripcion>ANGULO PERIMETRAL</descripcion><cantidad>35</cantidad><precioUnitario>0.8</precioUnitario><descuento>0</descuento><precioTotalSinImpuesto>28</precioTotalSinImpuesto><impuestos><impuesto><codigo>2</codigo><codigoPorcentaje>2</codigoPorcentaje><tarifa>12</tarifa><baseImponible>28</baseImponible><valor>3.36</valor></impuesto></impuestos></detalle><detalle><codigoPrincipal>pla.de .001</codigoPrincipal><descripcion>PLANCHA DE GYPSUM ST</descripcion><cantidad>7</cantidad><precioUnitario>9.38</precioUnitario><descuento>0</descuento><precioTotalSinImpuesto>65.66</precioTotalSinImpuesto><impuestos><impuesto><codigo>2</codigo><codigoPorcentaje>2</codigoPorcentaje><tarifa>12</tarifa><baseImponible>65.66</baseImponible><valor>7.88</valor></impuesto></impuestos></detalle><detalle><codigoPrincipal>ome.fur.001</codigoPrincipal><descripcion>OMEGA FURRIM 3.60 X 0.40</descripcion><cantidad>6</cantidad><precioUnitario>2.32</precioUnitario><descuento>0</descuento><precioTotalSinImpuesto>13.92</precioTotalSinImpuesto><impuestos><impuesto><codigo>2</codigo><codigoPorcentaje>2</codigoPorcentaje><tarifa>12</tarifa><baseImponible>13.92</baseImponible><valor>1.67</valor></impuesto></impuestos></detalle><detalle><codigoPrincipal>can.de .001</codigoPrincipal><descripcion>CANAL DE CARGA 3.60 X 0.40</descripcion><cantidad>10</cantidad><precioUnitario>2.23</precioUnitario><descuento>0</descuento><precioTotalSinImpuesto>22.3</precioTotalSinImpuesto><impuestos><impuesto><codigo>2</codigo><codigoPorcentaje>2</codigoPorcentaje><tarifa>12</tarifa><baseImponible>22.3</baseImponible><valor>2.68</valor></impuesto></impuestos></detalle><detalle><codigoPrincipal>tor.hid.001</codigoPrincipal><descripcion>TORNILLO 6X1 HIDO FINO CAJA MILLARES</descripcion><cantidad>1</cantidad><precioUnitario>7.14</precioUnitario><descuento>0</descuento><precioTotalSinImpuesto>7.14</precioTotalSinImpuesto><impuestos><impuesto><codigo>2</codigo><codigoPorcentaje>2</codigoPorcentaje><tarifa>12</tarifa><baseImponible>7.14</baseImponible><valor>0.86</valor></impuesto></impuestos></detalle><detalle><codigoPrincipal>tor.pun.001</codigoPrincipal><descripcion>TORNILLO PUNTA BROCA 8X1-2 X 100</descripcion><cantidad>6</cantidad><precioUnitario>1.07</precioUnitario><descuento>0</descuento><precioTotalSinImpuesto>6.42</precioTotalSinImpuesto><impuestos><impuesto><codigo>2</codigo><codigoPorcentaje>2</codigoPorcentaje><tarifa>12</tarifa><baseImponible>6.42</baseImponible><valor>0.77</valor></impuesto></impuestos></detalle><detalle><codigoPrincipal>rom.25 .001</codigoPrincipal><descripcion>ROMERAL 25 KL</descripcion><cantidad>1</cantidad><precioUnitario>19.64</precioUnitario><descuento>0</descuento><precioTotalSinImpuesto>19.64</precioTotalSinImpuesto><impuestos><impuesto><codigo>2</codigo><codigoPorcentaje>2</codigoPorcentaje><tarifa>12</tarifa><baseImponible>19.64</baseImponible><valor>2.36</valor></impuesto></impuestos></detalle><detalle><codigoPrincipal>cin.mal.001</codigoPrincipal><descripcion>CINTA MALLA DE FIBRA</descripcion><cantidad>1</cantidad><precioUnitario>3.13</precioUnitario><descuento>0</descuento><precioTotalSinImpuesto>3.13</precioTotalSinImpuesto><impuestos><impuesto><codigo>2</codigo><codigoPorcentaje>2</codigoPorcentaje><tarifa>12</tarifa><baseImponible>3.13</baseImponible><valor>0.38</valor></impuesto></impuestos></detalle><detalle><codigoPrincipal>sel. z-.001</codigoPrincipal><descripcion>SELLADOR WESCO Z-10  1 GALON</descripcion><cantidad>5</cantidad><precioUnitario>14.73</precioUnitario><descuento>0</descuento><precioTotalSinImpuesto>73.65</precioTotalSinImpuesto><impuestos><impuesto><codigo>2</codigo><codigoPorcentaje>2</codigoPorcentaje><tarifa>12</tarifa><baseImponible>73.65</baseImponible><valor>8.84</valor></impuesto></impuestos></detalle><detalle><codigoPrincipal>gal. we.001</codigoPrincipal><descripcion>GALON DE PINTURA WESCO BLANCO SATIN</descripcion><cantidad>5</cantidad><precioUnitario>19.64</precioUnitario><descuento>0</descuento><precioTotalSinImpuesto>98.2</precioTotalSinImpuesto><impuestos><impuesto><codigo>2</codigo><codigoPorcentaje>2</codigoPorcentaje><tarifa>12</tarifa><baseImponible>98.2</baseImponible><valor>11.78</valor></impuesto></impuestos></detalle></detalles><infoAdicional><campoAdicional nombre='Direccion'>CARLOS JULIO ROSEMENA</campoAdicional><campoAdicional nombre='Telefono'>0988989150</campoAdicional><campoAdicional nombre='Email'>animalhomemedicvet@hotmail.com</campoAdicional><campoAdicional nombre='Observaciones'> CONTRIBUYENTE REGIMEN RIMPE            </campoAdicional></infoAdicional></factura>