<?xml version='1.0' encoding='UTF-8'?><factura version='1.1.0' id='comprobante'><infoTributaria><ambiente>2</ambiente><tipoEmision>1</tipoEmision><razonSocial>OTAVALO UYAGUARI MANUEL EFRAIN</razonSocial><nombreComercial>OTAVALO UYAGUARI MANUEL EFRAIN</nombreComercial><ruc>0704642552001</ruc><claveAcceso>0106202301070464255200120010100000004011234567814</claveAcceso><codDoc>01</codDoc><estab>001</estab><ptoEmi>010</ptoEmi><secuencial>000000401</secuencial><dirMatriz>AZUAY Y MACHALA</dirMatriz></infoTributaria><infoFactura><fechaEmision>01/06/2023</fechaEmision><dirEstablecimiento>AZUAY Y MACAHALA</dirEstablecimiento><obligadoContabilidad>NO</obligadoContabilidad><tipoIdentificacionComprador>04</tipoIdentificacionComprador><razonSocialComprador>MOLINA PINEDA JOHNNY RICARDO</razonSocialComprador><identificacionComprador>0703939272001</identificacionComprador><totalSinImpuestos>545.92</totalSinImpuestos><totalDescuento>0</totalDescuento><totalConImpuestos><totalImpuesto><codigo>2</codigo><codigoPorcentaje>2</codigoPorcentaje><baseImponible>545.92</baseImponible><valor>65.51</valor></totalImpuesto></totalConImpuestos><propina>0.00</propina><importeTotal>611.43</importeTotal><moneda>DOLAR</moneda><pagos><pago><formaPago>01</formaPago><total>611.43</total></pago></pagos></infoFactura><detalles><detalle><codigoPrincipal>ang. pe.001</codigoPrincipal><descripcion>ANGULO PERIMETRAL</descripcion><cantidad>60</cantidad><precioUnitario>0.72</precioUnitario><descuento>0</descuento><precioTotalSinImpuesto>43.2</precioTotalSinImpuesto><impuestos><impuesto><codigo>2</codigo><codigoPorcentaje>2</codigoPorcentaje><tarifa>12</tarifa><baseImponible>43.2</baseImponible><valor>5.18</valor></impuesto></impuestos></detalle><detalle><codigoPrincipal>ome.fur.001</codigoPrincipal><descripcion>OMEGA FURRIM 3.60 X 0.40</descripcion><cantidad>40</cantidad><precioUnitario>2.05</precioUnitario><descuento>0</descuento><precioTotalSinImpuesto>82</precioTotalSinImpuesto><impuestos><impuesto><codigo>2</codigo><codigoPorcentaje>2</codigoPorcentaje><tarifa>12</tarifa><baseImponible>82</baseImponible><valor>9.84</valor></impuesto></impuestos></detalle><detalle><codigoPrincipal>can.de .001</codigoPrincipal><descripcion>CANAL DE CARGA 3.60 X 0.40</descripcion><cantidad>20</cantidad><precioUnitario>2.05</precioUnitario><descuento>0</descuento><precioTotalSinImpuesto>41</precioTotalSinImpuesto><impuestos><impuesto><codigo>2</codigo><codigoPorcentaje>2</codigoPorcentaje><tarifa>12</tarifa><baseImponible>41</baseImponible><valor>4.92</valor></impuesto></impuestos></detalle><detalle><codigoPrincipal>pla.de .001</codigoPrincipal><descripcion>PLANCHA DE GYPSUM ST</descripcion><cantidad>25</cantidad><precioUnitario>9.37</precioUnitario><descuento>0</descuento><precioTotalSinImpuesto>234.25</precioTotalSinImpuesto><impuestos><impuesto><codigo>2</codigo><codigoPorcentaje>2</codigoPorcentaje><tarifa>12</tarifa><baseImponible>234.25</baseImponible><valor>28.11</valor></impuesto></impuestos></detalle><detalle><codigoPrincipal>3/4.pla.001</codigoPrincipal><descripcion>PLANCHA GYPMSUM RH</descripcion><cantidad>3</cantidad><precioUnitario>13.39</precioUnitario><descuento>0</descuento><precioTotalSinImpuesto>40.17</precioTotalSinImpuesto><impuestos><impuesto><codigo>2</codigo><codigoPorcentaje>2</codigoPorcentaje><tarifa>12</tarifa><baseImponible>40.17</baseImponible><valor>4.82</valor></impuesto></impuestos></detalle><detalle><codigoPrincipal>TOR.PUN.002</codigoPrincipal><descripcion>TORNILLO PUNTA BROCA 8X1-2 X 1000</descripcion><cantidad>5</cantidad><precioUnitario>7.14</precioUnitario><descuento>0</descuento><precioTotalSinImpuesto>35.7</precioTotalSinImpuesto><impuestos><impuesto><codigo>2</codigo><codigoPorcentaje>2</codigoPorcentaje><tarifa>12</tarifa><baseImponible>35.7</baseImponible><valor>4.28</valor></impuesto></impuestos></detalle><detalle><codigoPrincipal>cin.mal.001</codigoPrincipal><descripcion>CINTA MALLA DE FIBRA</descripcion><cantidad>5</cantidad><precioUnitario>3.13</precioUnitario><descuento>0</descuento><precioTotalSinImpuesto>15.65</precioTotalSinImpuesto><impuestos><impuesto><codigo>2</codigo><codigoPorcentaje>2</codigoPorcentaje><tarifa>12</tarifa><baseImponible>15.65</baseImponible><valor>1.88</valor></impuesto></impuestos></detalle><detalle><codigoPrincipal>rom.25 .001</codigoPrincipal><descripcion>ROMERAL 25 KL</descripcion><cantidad>1</cantidad><precioUnitario>19.64</precioUnitario><descuento>0</descuento><precioTotalSinImpuesto>19.64</precioTotalSinImpuesto><impuestos><impuesto><codigo>2</codigo><codigoPorcentaje>2</codigoPorcentaje><tarifa>12</tarifa><baseImponible>19.64</baseImponible><valor>2.36</valor></impuesto></impuestos></detalle><detalle><codigoPrincipal>pun.pun.001</codigoPrincipal><descripcion>PUNTA ESTRELLA CON TOPE</descripcion><cantidad>3</cantidad><precioUnitario>0.89</precioUnitario><descuento>0</descuento><precioTotalSinImpuesto>2.67</precioTotalSinImpuesto><impuestos><impuesto><codigo>2</codigo><codigoPorcentaje>2</codigoPorcentaje><tarifa>12</tarifa><baseImponible>2.67</baseImponible><valor>0.32</valor></impuesto></impuestos></detalle><detalle><codigoPrincipal>est.tol.001</codigoPrincipal><descripcion>ESTILETE TOLSEN</descripcion><cantidad>2</cantidad><precioUnitario>1.34</precioUnitario><descuento>0</descuento><precioTotalSinImpuesto>2.68</precioTotalSinImpuesto><impuestos><impuesto><codigo>2</codigo><codigoPorcentaje>2</codigoPorcentaje><tarifa>12</tarifa><baseImponible>2.68</baseImponible><valor>0.32</valor></impuesto></impuestos></detalle><detalle><codigoPrincipal>rep.tol.001</codigoPrincipal><descripcion>REPUESTO DE RODILLO TOLSEN  9</descripcion><cantidad>2</cantidad><precioUnitario>1.34</precioUnitario><descuento>0</descuento><precioTotalSinImpuesto>2.68</precioTotalSinImpuesto><impuestos><impuesto><codigo>2</codigo><codigoPorcentaje>2</codigoPorcentaje><tarifa>12</tarifa><baseImponible>2.68</baseImponible><valor>0.32</valor></impuesto></impuestos></detalle><detalle><codigoPrincipal>des.des.001</codigoPrincipal><descripcion>DESARMADOR ESTRELLA MAVIJU</descripcion><cantidad>2</cantidad><precioUnitario>1.11</precioUnitario><descuento>0</descuento><precioTotalSinImpuesto>2.22</precioTotalSinImpuesto><impuestos><impuesto><codigo>2</codigo><codigoPorcentaje>2</codigoPorcentaje><tarifa>12</tarifa><baseImponible>2.22</baseImponible><valor>0.27</valor></impuesto></impuestos></detalle><detalle><codigoPrincipal>lap.ama.001</codigoPrincipal><descripcion>LAPIZ CARPINTERO AMARILLO STANLEY</descripcion><cantidad>2</cantidad><precioUnitario>0.67</precioUnitario><descuento>0</descuento><precioTotalSinImpuesto>1.34</precioTotalSinImpuesto><impuestos><impuesto><codigo>2</codigo><codigoPorcentaje>2</codigoPorcentaje><tarifa>12</tarifa><baseImponible>1.34</baseImponible><valor>0.16</valor></impuesto></impuestos></detalle><detalle><codigoPrincipal>cla.3/4.001</codigoPrincipal><descripcion>CLAVOS DE ACERO 3-4 100 UNIDADES MAXIMAR DGDIOLGOO</descripcion><cantidad>20</cantidad><precioUnitario>0.85</precioUnitario><descuento>0</descuento><precioTotalSinImpuesto>17</precioTotalSinImpuesto><impuestos><impuesto><codigo>2</codigo><codigoPorcentaje>2</codigoPorcentaje><tarifa>12</tarifa><baseImponible>17</baseImponible><valor>2.04</valor></impuesto></impuestos></detalle><detalle><codigoPrincipal>esp.n.5.001</codigoPrincipal><descripcion>ESPATULAS N.5  MAVIJU</descripcion><cantidad>2</cantidad><precioUnitario>2.86</precioUnitario><descuento>0</descuento><precioTotalSinImpuesto>5.72</precioTotalSinImpuesto><impuestos><impuesto><codigo>2</codigo><codigoPorcentaje>2</codigoPorcentaje><tarifa>12</tarifa><baseImponible>5.72</baseImponible><valor>0.69</valor></impuesto></impuestos></detalle></detalles><infoAdicional><campoAdicional nombre='Direccion'>PASAJE</campoAdicional><campoAdicional nombre='Telefono'>0969779359</campoAdicional><campoAdicional nombre='Email'>esfacon@gmail.com</campoAdicional><campoAdicional nombre='Observaciones'> CONTRIBUYENTE REGIMEN RIMPE            </campoAdicional></infoAdicional></factura>