<?xml version='1.0' encoding='UTF-8'?><factura version='1.1.0' id='comprobante'><infoTributaria><ambiente>2</ambiente><tipoEmision>1</tipoEmision><razonSocial>OTAVALO UYAGUARI MANUEL EFRAIN</razonSocial><nombreComercial>OTAVALO UYAGUARI MANUEL EFRAIN</nombreComercial><ruc>0704642552001</ruc><claveAcceso>1912202201070464255200120010100000000271234567817</claveAcceso><codDoc>01</codDoc><estab>001</estab><ptoEmi>010</ptoEmi><secuencial>000000027</secuencial><dirMatriz>AZUAY Y MACHALA</dirMatriz></infoTributaria><infoFactura><fechaEmision>19/12/2022</fechaEmision><dirEstablecimiento>AZUAY Y MACAHALA</dirEstablecimiento><obligadoContabilidad>NO</obligadoContabilidad><tipoIdentificacionComprador>04</tipoIdentificacionComprador><razonSocialComprador>FARES ROMERO PRISCILA ESTEFANIA</razonSocialComprador><identificacionComprador>0705399384001</identificacionComprador><totalSinImpuestos>0.49</totalSinImpuestos><totalDescuento>0</totalDescuento><totalConImpuestos><totalImpuesto><codigo>2</codigo><codigoPorcentaje>2</codigoPorcentaje><baseImponible>0.49</baseImponible><valor>0.06</valor></totalImpuesto></totalConImpuestos><propina>0.00</propina><importeTotal>0.55</importeTotal><moneda>DOLAR</moneda><pagos><pago><formaPago>01</formaPago><total>0.55</total></pago></pagos></infoFactura><detalles><detalle><codigoPrincipal>tee.2.001</codigoPrincipal><descripcion>TEE 2</descripcion><cantidad>1</cantidad><precioUnitario>0.49</precioUnitario><descuento>0</descuento><precioTotalSinImpuesto>0.49</precioTotalSinImpuesto><impuestos><impuesto><codigo>2</codigo><codigoPorcentaje>2</codigoPorcentaje><tarifa>12</tarifa><baseImponible>0.49</baseImponible><valor>0.06</valor></impuesto></impuestos></detalle></detalles><infoAdicional><campoAdicional nombre='Direccion'>PASAJE</campoAdicional><campoAdicional nombre='Telefono'>0994655461</campoAdicional><campoAdicional nombre='Email'>priscilafares@hotmail.com</campoAdicional><campoAdicional nombre='Observaciones'> CONTRIBUYENTE REGIMEN RIMPE            </campoAdicional></infoAdicional></factura>