<?xml version='1.0' encoding='UTF-8'?><factura version='1.1.0' id='comprobante'><infoTributaria><ambiente>2</ambiente><tipoEmision>1</tipoEmision><razonSocial>OTAVALO UYAGUARI MANUEL EFRAIN</razonSocial><nombreComercial>OTAVALO UYAGUARI MANUEL EFRAIN</nombreComercial><ruc>0704642552001</ruc><claveAcceso>2406202301070464255200120010100000004661234567811</claveAcceso><codDoc>01</codDoc><estab>001</estab><ptoEmi>010</ptoEmi><secuencial>000000466</secuencial><dirMatriz>AZUAY Y MACHALA</dirMatriz></infoTributaria><infoFactura><fechaEmision>24/06/2023</fechaEmision><dirEstablecimiento>AZUAY Y MACAHALA</dirEstablecimiento><obligadoContabilidad>NO</obligadoContabilidad><tipoIdentificacionComprador>05</tipoIdentificacionComprador><razonSocialComprador>PELAEZ JARA CARLOS ALBERTO</razonSocialComprador><identificacionComprador>0702654914</identificacionComprador><totalSinImpuestos>576.2</totalSinImpuestos><totalDescuento>0</totalDescuento><totalConImpuestos><totalImpuesto><codigo>2</codigo><codigoPorcentaje>2</codigoPorcentaje><baseImponible>576.2</baseImponible><valor>69.14</valor></totalImpuesto></totalConImpuestos><propina>0.00</propina><importeTotal>645.34</importeTotal><moneda>DOLAR</moneda><pagos><pago><formaPago>01</formaPago><total>645.34</total></pago></pagos></infoFactura><detalles><detalle><codigoPrincipal>due.3.9.001</codigoPrincipal><descripcion>DUELAS PVC 3.95X0.25 BLANCO</descripcion><cantidad>86</cantidad><precioUnitario>6.7</precioUnitario><descuento>0</descuento><precioTotalSinImpuesto>576.2</precioTotalSinImpuesto><impuestos><impuesto><codigo>2</codigo><codigoPorcentaje>2</codigoPorcentaje><tarifa>12</tarifa><baseImponible>576.2</baseImponible><valor>69.14</valor></impuesto></impuestos></detalle></detalles><infoAdicional><campoAdicional nombre='Direccion'>PASAJE</campoAdicional><campoAdicional nombre='Telefono'>0995530335</campoAdicional><campoAdicional nombre='Email'>cpelaezzara@gmail.com</campoAdicional><campoAdicional nombre='Observaciones'> CONTRIBUYENTE REGIMEN RIMPE            </campoAdicional></infoAdicional></factura>